cloudbreak/__init__.py
cloudbreak/__main__.py
cloudbreak/cloudbreak
cloudbreak/run
cloudbreak/app/__init__.py
cloudbreak/app/views.py
cloudbreak/app/dist/favicon.ico
cloudbreak/app/dist/index.html
cloudbreak/app/dist/manifest.json
cloudbreak/app/dist/precache-manifest.4ef45a68f2c56df5eefd6e0c3bbbe0ca.js
cloudbreak/app/dist/precache-manifest.e43158eee291cb768d51617ccfafa4b5.js
cloudbreak/app/dist/robots.txt
cloudbreak/app/dist/service-worker.js
cloudbreak/app/dist/img/icons/android-chrome-192x192.png
cloudbreak/app/dist/img/icons/android-chrome-512x512.png
cloudbreak/app/dist/img/icons/apple-touch-icon-120x120.png
cloudbreak/app/dist/img/icons/apple-touch-icon-152x152.png
cloudbreak/app/dist/img/icons/apple-touch-icon-180x180.png
cloudbreak/app/dist/img/icons/apple-touch-icon-60x60.png
cloudbreak/app/dist/img/icons/apple-touch-icon-76x76.png
cloudbreak/app/dist/img/icons/apple-touch-icon.png
cloudbreak/app/dist/img/icons/favicon-16x16.png
cloudbreak/app/dist/img/icons/favicon-32x32.png
cloudbreak/app/dist/img/icons/msapplication-icon-144x144.png
cloudbreak/app/dist/img/icons/mstile-150x150.png
cloudbreak/app/dist/img/icons/safari-pinned-tab.svg
cloudbreak/app/dist/static/css/app.d439ea00.css
cloudbreak/app/dist/static/css/chunk-vendors.dc9fa08f.css
cloudbreak/app/dist/static/js/app.9004f0f1.js
cloudbreak/app/dist/static/js/app.9004f0f1.js.map
cloudbreak/app/dist/static/js/app.a0090968.js
cloudbreak/app/dist/static/js/app.a0090968.js.map
cloudbreak/app/dist/static/js/chunk-vendors.5b00b76f.js
cloudbreak/app/dist/static/js/chunk-vendors.5b00b76f.js.map
cloudbreak/torrent/__init__.py
cloudbreak/torrent/client.py
cloudbreak-0.1.1.data/scripts/cloudbreak
cloudbreak-0.1.1.data/scripts/run
cloudbreak-0.1.1.dist-info/LICENSE
cloudbreak-0.1.1.dist-info/METADATA
cloudbreak-0.1.1.dist-info/WHEEL
cloudbreak-0.1.1.dist-info/top_level.txt
cloudbreak-0.1.1.dist-info/RECORD
