Metadata-Version: 2.1
Name: cloudbreak
Version: 0.1.1
Summary: A material design web UI for deluge
Home-page: https://github.com/nat212/cloudbreak
Author: Natasha Draper
Author-email: natasha@draper.net.za
License: UNKNOWN
Platform: UNKNOWN
Classifier: Programming Language :: Python :: 3
Classifier: Operating System :: OS Independent
Requires-Dist: deluge
Requires-Dist: twisted
Requires-Dist: flask
Requires-Dist: crochet
Requires-Dist: service-identity
Requires-Dist: flask-cors
